rtl/branch_predictors.v
module predictor (
    input wire clk,
    input wire rst_n,
    input wire x,       // current observed bit
    output wire pred    // prediction for next bit
);

    // Internal learning rate (observable in simulation)
    reg [1:0] ctr;

    // Combinational predition from current state
    // ctr = 2,3 -> predict 1
    // ctr = 0,1 -> predict 0
    assign pred = ctr[1];

    // Sequential learning rule
    always @(posedge clk) begin
        if (!rst_n) begin
            // Weakly biased initial state (design choice)
            ctr <= 2'b01;
        end else begin
            if (x) begin
                // Increment toward strongly-1
                if (ctr != 2'b11)
                    ctr <= ctr + 1'b1;
            end else begin
                // Decrement toward strongly-0
                if (ctr != 2'b00)
                    ctr <= ctr - 1'b1;
            end
        end
    end
endmodule

tb/tb_predictor.v
`timescale 1ns/1ps

module tb_predictor;

    // Clock and reset
    reg clk = 0;
    reg rst_n = 0;

    // Input stream
    reg x;

    // DUT output
    wire pred;

    // Observer-only signals
    reg pred_prev;
    reg correct;

    // Instantiate DUT
    predictor dut (
        .clk  (clk),
        .rst_n(rst_n),
        .x    (x),
        .pred (pred)
    );

    // Clock generation: 10ns period
    always #5 clk = ~clk;

    // Save prediction and compute correctness
    always @(posedge clk) begin
        pred_prev <= pred;
        correct   <= (pred_prev == x);
    end

    // Stimulus
    initial begin
        // Waveform dump
        $dumpfile("wave.vcd");
        $dumpvars(0, tb_predictor);

        // Initial conditions
        x = 0;

        // Apply reset for a few cycles
        #12;
        rst_n = 1;

        // -------- Test 1: steady 1s --------
        repeat (10) begin
            @(posedge clk);
            x <= 1'b1;
        end

        // -------- Test 2: steady 0s --------
        repeat (10) begin
            @(posedge clk);
            x <= 1'b0;
        end

        // -------- Test 3: alternating --------
        repeat (10) begin
            @(posedge clk);
            x <= ~x;
        end

        // Finish
        #20;
        $finish;
    end

endmodule

sim/wave.vcd
$date
	Mon Mar  2 10:19:34 2026
$end
$version
	Icarus Verilog
$end
$timescale
	1ps
$end
$scope module tb_predictor $end
$var wire 1 ! pred $end
$var reg 1 " clk $end
$var reg 1 # correct $end
$var reg 1 $ pred_prev $end
$var reg 1 % rst_n $end
$var reg 1 & x $end
$scope module dut $end
$var wire 1 " clk $end
$var wire 1 % rst_n $end
$var wire 1 & x $end
$var wire 1 ! pred $end
$var reg 2 ' ctr [1:0] $end
$upscope $end
$upscope $end
$enddefinitions $end
$comment Show the parameter values. $end
$dumpall
$end
#0
$dumpvars
bx '
0&
0%
x$
x#
0"
x!
$end
#5000
0!
b1 '
1"
#10000
0"
#12000
1%
#15000
0$
b0 '
1&
1"
#20000
0"
#25000
b1 '
0#
1"
#30000
0"
#35000
1!
b10 '
1"
#40000
0"
#45000
b11 '
1$
1"
#50000
0"
#55000
1#
1"
#60000
0"
#65000
1"
#70000
0"
#75000
1"
#80000
0"
#85000
1"
#90000
0"
#95000
1"
#100000
0"
#105000
1"
#110000
0"
#115000
0&
1"
#120000
0"
#125000
b10 '
0#
1"
#130000
0"
#135000
0!
b1 '
1"
#140000
0"
#145000
b0 '
0$
1"
#150000
0"
#155000
1#
1"
#160000
0"
#165000
1"
#170000
0"
#175000
1"
#180000
0"
#185000
1"
#190000
0"
#195000
1"
#200000
0"
#205000
1"
#210000
0"
#215000
1&
1"
#220000
0"
#225000
0&
b1 '
0#
1"
#230000
0"
#235000
1#
b0 '
1&
1"
#240000
0"
#245000
0&
b1 '
0#
1"
#250000
0"
#255000
1#
b0 '
1&
1"
#260000
0"
#265000
0&
b1 '
0#
1"
#270000
0"
#275000
1#
b0 '
1&
1"
#280000
0"
#285000
0&
b1 '
0#
1"
#290000
0"
#295000
1#
b0 '
1&
1"
#300000
0"
#305000
0&
b1 '
0#
1"
#310000
0"
#315000
1#
b0 '
1"
